sagemaker/__init__.py
sagemaker/serve/__init__.py
sagemaker/serve/bedrock_model_builder.py
sagemaker/serve/configs.py
sagemaker/serve/constants.py
sagemaker/serve/deployment_progress.py
sagemaker/serve/inference_recommendation_mixin.py
sagemaker/serve/local_resources.py
sagemaker/serve/model_builder.py
sagemaker/serve/model_builder_servers.py
sagemaker/serve/model_builder_utils.py
sagemaker/serve/predictor_async.py
sagemaker/serve/async_inference/__init__.py
sagemaker/serve/async_inference/async_inference_config.py
sagemaker/serve/async_inference/async_inference_response.py
sagemaker/serve/async_inference/waiter_config.py
sagemaker/serve/batch_inference/__init__.py
sagemaker/serve/batch_inference/batch_transform_inference_config.py
sagemaker/serve/builder/__init__.py
sagemaker/serve/builder/requirements_manager.py
sagemaker/serve/builder/schema_builder.py
sagemaker/serve/builder/serve_settings.py
sagemaker/serve/builder/triton_schema_builder.py
sagemaker/serve/compute_resource_requirements/__init__.py
sagemaker/serve/compute_resource_requirements/resource_requirements.py
sagemaker/serve/detector/__init__.py
sagemaker/serve/detector/dependency_manager.py
sagemaker/serve/detector/image_detector.py
sagemaker/serve/detector/pickle_dependencies.py
sagemaker/serve/detector/pickler.py
sagemaker/serve/marshalling/__init__.py
sagemaker/serve/marshalling/custom_payload_translator.py
sagemaker/serve/marshalling/triton_translator.py
sagemaker/serve/mode/__init__.py
sagemaker/serve/mode/function_pointers.py
sagemaker/serve/mode/in_process_mode.py
sagemaker/serve/mode/local_container_mode.py
sagemaker/serve/mode/sagemaker_endpoint_mode.py
sagemaker/serve/model_format/__init__.py
sagemaker/serve/model_format/mlflow/__init__.py
sagemaker/serve/model_format/mlflow/constants.py
sagemaker/serve/model_format/mlflow/utils.py
sagemaker/serve/model_server/__init__.py
sagemaker/serve/model_server/djl_serving/__init__.py
sagemaker/serve/model_server/djl_serving/prepare.py
sagemaker_serve-1.3.0.dist-info/METADATA
sagemaker_serve-1.3.0.dist-info/WHEEL
sagemaker_serve-1.3.0.dist-info/top_level.txt
sagemaker_serve-1.3.0.dist-info/RECORD
