Metadata-Version: 2.4
Name: sagemaker-serve
Version: 1.3.0
Summary: SageMaker Serve package for model serving and deployment
Author: Amazon Web Services
Classifier: Development Status :: 3 - Alpha
Classifier: Intended Audience :: Developers
Classifier: License :: OSI Approved :: Apache Software License
Classifier: Programming Language :: Python :: 3
Classifier: Programming Language :: Python :: 3.9
Classifier: Programming Language :: Python :: 3.10
Classifier: Programming Language :: Python :: 3.11
Classifier: Programming Language :: Python :: 3.12
Requires-Python: >=3.9
Requires-Dist: sagemaker-core>=2.3.0
Requires-Dist: sagemaker-train>=1.3.0
Requires-Dist: boto3<2.0,>=1.42.2
Requires-Dist: botocore<2.0,>=1.35.75
Requires-Dist: deepdiff
Requires-Dist: mlflow
Requires-Dist: sagemaker_schema_inference_artifacts
Requires-Dist: pytest
Requires-Dist: tqdm
Requires-Dist: psutil
Requires-Dist: tritonclient[http]
Requires-Dist: onnx
Requires-Dist: onnxruntime
Requires-Dist: torch>=2.0.0
Provides-Extra: test
Requires-Dist: pytest; extra == "test"
Requires-Dist: pytest-cov; extra == "test"
Requires-Dist: mock; extra == "test"
Provides-Extra: dev
Requires-Dist: pytest; extra == "dev"
Requires-Dist: pytest-cov; extra == "dev"
Requires-Dist: mock; extra == "dev"
Requires-Dist: black; extra == "dev"
Requires-Dist: flake8; extra == "dev"
